PhraseCraft/__init__.py
PhraseCraft/build_phrasec.py
PhraseCraft/eef_wordlist.txt
PhraseCraft/phrasec.py
phrasec-0.1.3.dist-info/LICENSE
phrasec-0.1.3.dist-info/METADATA
phrasec-0.1.3.dist-info/WHEEL
phrasec-0.1.3.dist-info/entry_points.txt
phrasec-0.1.3.dist-info/top_level.txt
phrasec-0.1.3.dist-info/RECORD
