Metadata-Version: 2.1
Name: phrasec
Version: 0.1.3
Summary: PassPhrase generator CLI
Author: Emil Larsson
Author-email: emil@wirely.se
License: MIT
Classifier: Development Status :: 3 - Alpha
Classifier: Environment :: Console
Classifier: Operating System :: OS Independent
Classifier: Programming Language :: Python :: 3
Classifier: Topic :: Software Development
License-File: LICENSE
Requires-Dist: Click
